eeghdf/__init__.py
eeghdf/convert.py
eeghdf/reader.py
eeghdf/writer.py
eeghdf-0.2.4.dist-info/LICENSE
eeghdf-0.2.4.dist-info/WHEEL
eeghdf-0.2.4.dist-info/METADATA
eeghdf-0.2.4.dist-info/RECORD
