Metadata-Version: 2.1
Name: eeghdf
Version: 0.2.4
Summary: eeghdf is a module for reading a writing EEG data into the hdf5 format
Author-email: Chris Lee-Messer <chris@lee-messer.net>
Requires-Python: >=3.7
Classifier: Intended Audience :: Science/Research
Classifier: License :: OSI Approved :: BSD License
Classifier: Topic :: Scientific/Engineering :: Medical Science Apps.
Classifier: Development Status :: 4 - Beta
Requires-Dist: numpy
Requires-Dist: h5py
Requires-Dist: pandas
Requires-Dist: future
Requires-Dist: mne>=1.0 ; extra == "mne"
Requires-Dist: pytest ; extra == "test"
Requires-Dist: dynaconf>=3.0 ; extra == "test"
Project-URL: Home, https://github.com/eegml/eeghdf
Provides-Extra: mne
Provides-Extra: test
